affo_email_client/__init__.py
affo_email_client-1.0.1.dist-info/METADATA
affo_email_client-1.0.1.dist-info/WHEEL
affo_email_client-1.0.1.dist-info/top_level.txt
affo_email_client-1.0.1.dist-info/RECORD
