Metadata-Version: 2.1
Name: affo-email-client
Version: 1.0.1
Summary: UNKNOWN
Home-page: https://github.com/affoio/affo-email-client
Author: Aleksey Dalekin
Author-email: ald@affo.io
License: BSD
Keywords: email service client
Platform: any
Classifier: Development Status :: 3 - Alpha
Classifier: License :: OSI Approved :: BSD License
Classifier: Topic :: System :: Distributed Computing
Classifier: Intended Audience :: Developers
Classifier: Programming Language :: Python
Classifier: Programming Language :: Python :: 3.5
Classifier: Programming Language :: Python :: 3.6
Classifier: Programming Language :: Python :: 3.7
Classifier: Programming Language :: Python :: Implementation :: CPython
Classifier: Operating System :: OS Independent
Requires-Dist: simple-rest-client (>=0.5.4)
